pysyrenn/__init__.py
pysyrenn/frontend/__init__.py
pysyrenn/frontend/argmax_layer.py
pysyrenn/frontend/averagepool_layer.py
pysyrenn/frontend/concat_layer.py
pysyrenn/frontend/conv2d_layer.py
pysyrenn/frontend/fullyconnected_layer.py
pysyrenn/frontend/hard_tanh_layer.py
pysyrenn/frontend/layer.py
pysyrenn/frontend/maxpool_layer.py
pysyrenn/frontend/network.py
pysyrenn/frontend/normalize_layer.py
pysyrenn/frontend/relu_layer.py
pysyrenn/frontend/strided_window_data.py
pysyrenn/frontend/transformer_client.py
pysyrenn/helpers/__init__.py
pysyrenn/helpers/classify_lines.py
pysyrenn/helpers/classify_planes.py
pysyrenn/helpers/integrated_gradients.py
pysyrenn/helpers/masking_network.py
pysyrenn/helpers/netpatch.py
syrenn_proto/__init__.py
syrenn_proto/syrenn_pb2.py
syrenn_proto/syrenn_pb2_grpc.py
pysyrenn-1.1.dist-info/LICENSE
pysyrenn-1.1.dist-info/METADATA
pysyrenn-1.1.dist-info/WHEEL
pysyrenn-1.1.dist-info/top_level.txt
pysyrenn-1.1.dist-info/RECORD
